{"cameraMode":{"drawMode":0,"name":"Shaded","section":"Shading Mode"},"sceneLighting":true,"audioPlay":false,"sceneViewState":{"showFog":true,"showMaterialUpdate":false,"showSkybox":true,"showFlares":true,"showImageEffects":true,"showParticleSystems":true},"in2DMode":false,"pivot":{"x":45.19977951049805,"y":0.4885788559913635,"z":28.43739128112793},"rotation":{"x":-0.16079457104206086,"y":-0.4353640377521515,"z":0.07942334562540055,"w":-0.8822607398033142},"size":0.717383086681366,"orthographic":false}